indiayz/__init__.py
indiayz/chat.py
indiayz/client.py
indiayz/exceptions.py
indiayz/media.py
indiayz/quote.py
indiayz/wikipedia.py
indiayz-0.2.7.dist-info/licenses/LICENSE
indiayz-0.2.7.dist-info/METADATA
indiayz-0.2.7.dist-info/WHEEL
indiayz-0.2.7.dist-info/top_level.txt
indiayz-0.2.7.dist-info/RECORD
