Metadata-Version: 2.4
Name: indiayz
Version: 0.2.7
Summary: Unified open-source AI toolkit with a clean, modular Python SDK
Author-email: indiayz <support@indiayz.ai>
License: Apache-2.0
Project-URL: Homepage, https://github.com/indiayz/indiayz-ai
Project-URL: Repository, https://github.com/indiayz/indiayz-ai
Project-URL: Issues, https://github.com/indiayz/indiayz-ai/issues
Project-URL: Documentation, https://github.com/indiayz/indiayz-ai#readme
Keywords: ai,llm,machine-learning,sdk,open-source,artificial-intelligence
Classifier: Development Status :: 3 - Alpha
Classifier: Intended Audience :: Developers
Classifier: License :: OSI Approved :: Apache Software License
Classifier: Operating System :: OS Independent
Classifier: Programming Language :: Python :: 3
Classifier: Programming Language :: Python :: 3.9
Classifier: Programming Language :: Python :: 3.10
Classifier: Programming Language :: Python :: 3.11
Classifier: Typing :: Typed
Requires-Python: >=3.9
License-File: LICENSE
Provides-Extra: dev
Requires-Dist: pytest; extra == "dev"
Requires-Dist: black; extra == "dev"
Requires-Dist: ruff; extra == "dev"
Requires-Dist: mypy; extra == "dev"
Dynamic: license-file
